{
"meta":{"test_sets":[],"test_metrics":[],"learn_metrics":[{"best_value":"Min","name":"Logloss"}],"launch_mode":"Train","parameters":"","iteration_count":500,"learn_sets":["learn"],"name":"experiment"},
"iterations":[
{"learn":[0.5999655161],"iteration":0,"passed_time":0.02597129144,"remaining_time":12.95967443,,
{"learn":[0.5020539176],"iteration":1,"passed_time":0.04964873116,"remaining_time":12.3625340,,,
{"learn":[0.435915016],"iteration":2,"passed_time":0.073673007,"remaining_time":12.20516149},,
{"learn":[0.3635357786],"iteration":3,"passed_time":0.1369330139,"remaining_time":16.97969372,,
{"learn":[0.3209876996],"iteration":4,"passed_time":0.1679377207,"remaining_time":16.62583434,,
{"learn":[0.2798728514],"iteration":5,"passed_time":0.1969992869,"remaining_time":16.2196079,
,
{"learn":[0.2515652462],"iteration":6,"passed_time":0.2275176981,"remaining_time":16.0237464,,,
{"learn":[0.2217708805],"iteration":7,"passed_time":0.2543980801,"remaining_time":15.6454819,,,
{"learn":[0.2036989419],"iteration":8,"passed_time":0.2872301349,"remaining_time":15.66999958,,
{"learn":[0.1798232579],"iteration":9,"passed_time":0.31491419,"remaining_time":15.43079531},
{"learn":[0.1667033372],"iteration":10,"passed_time":0.3396165963,"remaining_time":15.09750142,,
{"learn":[0.1507887982],"iteration":11,"passed_time":0.3653033854,"remaining_time":14.85567101},
{"learn":[0.1381709759],"iteration":12,"passed_time":0.3947334129,"remaining_time":14.78732093,,
{"learn":[0.1306320331],"iteration":13,"passed_time":0.4246342775,"remaining_time":14.74087563},
{"learn":[0.1221900964],"iteration":14,"passed_time":0.4561489467,"remaining_time":14.74881594},
{"learn":[0.1148200376],"iteration":15,"passed_time":0.4840475036,"remaining_time":14.64243698,,
{"learn":[0.1086980272],"iteration":16,"passed_time":0.515884217,"remaining_time":14.65718099,,
{"learn":[0.1050214988],"iteration":17,"passed_time":0.5392536543,"remaining_time":14.44001452,
{"learn":[0.09570196725],"iteration":18,"passed_time":0.5286802362,"remaining_time":13.38395756},
{"learn":[0.0898780516],"iteration":19,"passed_time":0.5598593611,"remaining_time":13.43662467},
{"learn":[0.0837896554],"iteration":20,"passed_time":0.5900617281,"remaining_time":13.45902704},
{"learn":[0.0812901359],"iteration":21,"passed_time":0.6205761392,"remaining_time":13.48342703},
{"learn":[0.07840853435],"iteration":22,"passed_time":0.6497548314,"remaining_time":13.4753502},
{"learn":[0.07515479711],"iteration":23,"passed_time":0.6801873669,"remaining_time":13.49038278},
{"learn":[0.07231999717],"iteration":24,"passed_time":0.707158958,"remaining_time":13.4360202},
{"learn":[0.07069099504],"iteration":25,"passed_time":0.7368726544,"remaining_time":13.43375532},
{"learn":[0.06834431488],"iteration":26,"passed_time":0.7659503041,"remaining_time":13.41831459},
{"learn":[0.06505416474],"iteration":27,"passed_time":0.7955824999,"remaining_time":13.41124785},
{"learn":[0.06376603252],"iteration":28,"passed_time":0.8232895969,"remaining_time":13.37135863},
{"learn":[0.06136669115],"iteration":29,"passed_time":0.8479910865,"remaining_time":13.28519369},
{"learn":[0.05999587078],"iteration":30,"passed_time":0.8778490757,"remaining_time":13.28100698},
{"learn":[0.05911666],"iteration":31,"passed_time":0.912748897,"remaining_time":13.34895262},
{"learn":[0.05678939297],"iteration":32,"passed_time":0.9384305195,"remaining_time":13.28021371},
{"learn":[0.05596140684],"iteration":33,"passed_time":0.9747156019,"remaining_time":13.35933737},
{"learn":[0.0551253409],"iteration":34,"passed_time":1.018147158,"remaining_time":13.52681225},
{"learn":[0.0544900786],"iteration":35,"passed_time":1.066867924,"remaining_time":13.75074213},
{"learn":[0.05323203265],"iteration":36,"passed_time":1.130323349,"remaining_time":14.1443165},
{"learn":[0.05230971125],"iteration":37,"passed_time":1.184339073,"remaining_time":14.39906979},
{"learn":[0.05119376031],"iteration":38,"passed_time":1.232840712,"remaining_time":14.57280944},
{"learn":[0.05015470781],"iteration":39,"passed_time":1.282345567,"remaining_time":14.74697402},
{"learn":[0.0494344805],"iteration":40,"passed_time":1.407139067,"remaining_time":15.75309346},
{"learn":[0.04890005752],"iteration":41,"passed_time":1.61330126,"remaining_time":17.59266613},
{"learn":[0.04736683683],"iteration":42,"passed_time":1.75907522,"remaining_time":18.6952878},
{"learn":[0.04624028064],"iteration":43,"passed_time":1.867515297,"remaining_time":19.35424945},
{"learn":[0.04513025076],"iteration":44,"passed_time":1.90905038,"remaining_time":19.30262051},
{"learn":[0.04452285609],"iteration":45,"passed_time":1.974008984,"remaining_time":19.48261041},
{"learn":[0.04355050529],"iteration":46,"passed_time":1.991687751,"remaining_time":19.19647981},
{"learn":[0.04291758889],"iteration":47,"passed_time":2.127657674,"remaining_time":20.03544309},
{"learn":[0.04219913469],"iteration":48,"passed_time":2.190931472,"remaining_time":20.16551212},
{"learn":[0.04125479685],"iteration":49,"passed_time":2.20495196,"remaining_time":19.844567,
{,
{"learn":[0.04035850958],"iteration":50,"passed_time":2.304487007,"remaining_time":20.288522,
{"lear,
{"learn":[0.03674665879],"iteration":51,"passed_time":2.430522934,"remaining_time":20.9,
{,
{"learn":[0.0390976186],"iteration":52,"passed_time":2.451981272,"remaining_time":20.67991752},
{"learn":[0.03865738286],"iteration":53,"passed_time":2.507294924,"remaining_time":20.70839882},
{"learn":[0.03825328542],"iteration":54,"passed_time":2.588786327,"remaining_time":20.94563483},
{"learn":[0.03756477956],"iteration":55,"passed_time":2.687052281,"remaining_time":21.30448594},
{"learn":[0.,
{"learn":[0.03725714296],"iteration":56,"passed_time":2.778581889,"remaining_tim,
{"learn":[0.03677159654],"iteration":57,"passed_time":2.869603994,"remaining_time":21.86836147},
{"learn":[0.0360488616],"iteration":58,"passed_time":2.914045183,"remaining_time":21.78125298},
{"learn":[0.03573458219],"iteration":59,"passed_time":3.008929902,"remaining_time":22.06548595},
{"learn":[0.03510537704],"iteration":60,"passed_time":3.108206322,"remaining_time":22.36889468},
{"learn":[0.03455751925],"iteration":61,"passed_time":3.186406282,"remaining_time":22.51041857},
{"learn":[0.03391688889],"iteration":62,"passed_time":3.24539888,"remaining_time":22.51173509},
{"learn":[0.03298952852],"iteration":63,"passed_time":3.339884012,"remaining_time":22.75295983},
{"learn":[0.03180962279],"iteration":64,"passed_time":3.357664029,"remaining_time":22.47052081},
{"learn":[0.03138035015],"iteration":65,"passed_time":3.459031592,"remaining_time":22.74575319},
{"learn":[0.03113909216],"iteration":66,"passed_time":3.546385458,"remaining_time":22.91917766},
{"learn":[0.03062458707],"iteration":67,"passed_time":3.559899858,"remaining_time":22.61583439},
{"learn":[0.0300312432],"iteration":68,"passed_time":3.729857012,"remaining_time":23.29809235},
{"learn":[0.02952790184],"iteration":69,"passed_time":3.86916192,"remaining_time":23.76770893},
{"learn":[0.02923987116],"iteration":70,"passed_time":3.910714419,"remaining_time":23.62952797},
{"learn":[0.02895167562],"iteration":71,"passed_time":4.006853398,"remaining_time":23.81851742},
{"learn":[0.02864568036],"iteration":72,"passed_time":4.021560141,"remaining_time":23.52337,
{",
{"learn":[0.02837344573],"iteration":73,"passed_time":4.213972141,"remaining_time":24.25881259},
{"learn":[0.02794359746],"iteration":74,"passed_time":4.26156348,"remaining_time":24.1488,
{"l,
{"le,
{"learn":[0.02458953836],"iteration":75,"passed_time":4.416637681,"remaining_time":24.64,
{"learn":[0.02731373415],"iteration":76,"passed_time":4.465180195,"remaining_time":24.5294964},
{"learn":[0.02700183258],"iteration":77,"passed_time":4.478916222,"remaining_time":24.232085,
,
{"learn":[0.02674127938],"iteration":78,"passed_time":4.590479866,"remaining_time":24.46319017},
{"learn":[0.02642365456],"iteration":79,"passed_time":4.68794123,"remaining_time":24.61169146},
{"learn":[0.02603882773],"iteration":80,"passed_time":4.760332269,"remaining_time":24.62443482},
{"lear,
{"learn":[0.02262925024],"iteration":81,"passed_time":4.866279909,"remaining_time":24.8,
{"learn":[0.02513615611],"iteration":82,"passed_time":4.94848886,"remaining_time":24.86168499},
{"learn,
{"learn":[0.02186683745],"iteration":83,"passed_time":5.134857228,"remaining_time":25.42976913},
{"learn":[0.02165998704],"iteration":84,"passed_time":5.159233507,"remaining_time":25.,
{"learn,
{"learn":[0.02136275871],"iteration":85,"passed_time":5.250130068,"remaining_time":25.,
{"learn,
{"learn":[0.02106264421],"iteration":86,"passed_time":5.352150136,"remaining_time":25,
{"learn":[0.02272411603],"iteration":87,"passed_time":5.38183929,"remaining_time":25.19679304},
{"learn",
{"learn":[0.02025625632],"iteration":88,"passed_time":5.524172556,"remaining_time":2,
{"learn":,
{"learn":[0.01993972887],"iteration":89,"passed_time":5.623563519,"remaining_time":2,
{"learn":[0.02187549683],"iteration":90,"passed_time":5.701587227,"remaining_time":25.62581512},
{"learn":[0.02167521929],"iteration":91,"passed_time":5.776959373,"remaining_time":25.61955896},
{"learn",
{"learn":[0.01916458659],"iteration":92,"passed_time":5.905176025,"remaining_time":25,
{"learn",
{"learn":[0.01885755071],"iteration":93,"passed_time":6.002933184,"remaining_time":25.92756247},
{"learn":[0.01843727929],"iteration":94,"passed_time":6.019614651,"remaining_time":,
{"learn":[0.02036700712],"iteration":95,"passed_time":6.131187378,"remaining_time":25.80208022},
{"learn":[0.01994167034],"iteration":96,"passed_time":6.167318126,"remaining_time":25.62298149},
{"learn":[0.01964566936],"iteration":97,"passed_time":6.180773442,"remaining_time":25.35378494},
{"learn":[,
{"learn":[0.01712456875],"iteration":98,"passed_time":6.385249414,"remaining_time":25.863485},
{"learn":[0.0169450097],"iteration":99,"passed_time":6.464760218,"remaining_time":25.85904087},
{"learn":[0.01669873656],"iteration":100,"passed_time":6.530941665,"remaining_time":25.80045271},
{"learn":[0.01649717442],"iteration":101,"passed_time":6.592705201,"remaining_time":25.72447716},
{"learn":[0.01628086573],"iteration":102,"passed_time":6.608301493,"remaining_time":2,
{"learn":[0.01812123432],"iteration":103,"passed_time":6.646409881,"remaining_time":25.30748378},
{"learn":[0.01787498536],"iteration":104,"passed_time":6.736451395,"remaining_time":25.34188858},
{"learn":[0.01756074373],"iteration":105,"passed_time":6.790233992,"remaining_time":25.23917,
{",
{"learn":[0.01738142609],"iteration":106,"passed_time":6.841655779,"remaining_time":25.12869833},
{"learn":[0.01709254302],"iteration":107,"passed_time":6.92968086,"remaining_time":25.15217497},
{"learn":[0.01696617366],"iteration":108,"passed_time":6.988269579,"remaining_time":25.068012,
{,
{"learn":[0.01668532456],"iteration":109,"passed_time":7.166413507,"remaining_time":25.40819334},
{"learn":[0.01647646832],"iteration":110,"passed_time":7.180226117,"remaining_time":25.16313477},
{"learn":[0.01633002178],"iteration":111,"passed_time":7.306029834,"remaining_time":25.31017478},
{"learn":[0.01613907555],"iteration":112,"passed_time":7.444402942,"remaining_time":25.49543309},
{"learn":[0.01599790657],"iteration":113,"passed_time":7.544102075,"remaining_time":25.54406492},
{"learn":[0.01572246099],"iteration":114,"passed_time":7.6533767,"remaining_time":25.62217417},
{"learn":[0.01553890164],"iteration":115,"passed_time":7.793709366,"remaining_time":25.79986549},
{"learn":[0.01542242888],"iteration":116,"passed_time":7.849199103,"remaining_time":25.69438681},
{"learn":[0.01524517896],"iteration":117,"passed_time":7.865520233,"remaining_time":25.46295533},
{"learn":[0.0151376098],"iteration":118,"passed_time":7.963532352,"remaining_time":25.49668761},
{"learn":[0.01499150226],"iteration":119,"passed_time":8.097927721,"remaining_time":25.64343778},
{"learn":[0.01491471571],"iteration":120,"passed_time":8.168431577,"remaining_time":25.58541792},
{"learn":[0.0146245528],"iteration":121,"passed_time":8.299972798,"remaining_time":25.71630916},
{"learn":[0.01451706387],"iteration":122,"passed_time":8.331401383,"remaining_time":25.53608391},
{"learn":[0.01440964571],"iteration":123,"passed_time":8.444109786,"remaining_time":25.60472},
{"learn":[0.01427937155],"iteration":124,"passed_time":8.457602269,"remaining_time":25.37280681},
{"learn":[0.01414511158],"iteration":125,"passed_time":8.475262244,"remaining_time":25.15673079},
{"learn":[0.01401552714],"iteration":126,"passed_time":8.681573189,"remaining_time":25.49784881},
{"learn":[0.01391403287],"iteration":127,"passed_time":8.798544001,"remaining_time":25.5707685},
{"learn":[0.01380093908],"iteration":128,"passed_time":8.939020752,"remaining_time":25.7083465},
{"learn":[0.01360973769],"iteration":129,"passed_time":9.019110269,"remaining_time":25.66977538},
{"learn":[0.01353141935],"iteration":130,"passed_time":9.185405893,"remaining_time":25.87339522},
{"learn":[0.01336303087],"iteration":131,"passed_time":9.254211652,"remaining_time":25.79962036},
{"learn":[0.01314279602],"iteration":132,"passed_time":9.412543296,"remaining_time":25.97295782},
{"learn":[0.01298956797],"iteration":133,"passed_time":9.466010433,"remaining_time":25.85492402},
{"learn":[0.01281920788],"iteration":134,"passed_time":9.505496208,"remaining_time":25.7000453},
{"learn":[0.01273265998],"iteration":135,"passed_time":9.541103284,"remaining_time":25.53648232},
{"learn":[0.01236787363],"iteration":136,"passed_time":9.581466983,"remaining_time":25.38739062},
{"learn":[0.01218732602],"iteration":137,"passed_time":9.650399035,"remaining_time":25.31481486},
{"learn":[0.01198141739],"iteration":138,"passed_time":9.715789726,"remaining_time":25.23309418},
{"learn":[0.01184781631],"iteration":139,"passed_time":9.753419361,"remaining_time":25.08022121},
{"learn":[0.01171088473],"iteration":140,"passed_time":9.829391136,"remaining_time":25.0266058},
{"learn":[0.01154322544],"iteration":141,"passed_time":9.874555206,"remaining_time":24.89500538},
{"learn":[0.01143346029],"iteration":142,"passed_time":9.941038406,"remaining_time":24.81783714},
{"learn":[0.01127722786],"iteration":143,"passed_time":9.988607995,"remaining_time":24.69405865},
{"learn":[0.01116675448],"iteration":144,"passed_time":10.05289434,"remaining_time":24.61225857},
{"learn":[0.01106388748],"iteration":145,"passed_time":10.14880165,"remaining_time":24.60736839},
{"learn":[0.01099082818],"iteration":146,"passed_time":10.20857801,"remaining_time":24.51447644},
{"learn":[0.01084938004],"iteration":147,"passed_time":10.25484813,"remaining_time":24.38990906},
{"learn":[0.01070410342],"iteration":148,"passed_time":10.31386302,"remaining_time":24.29641557},
{"learn":[0.01056688909],"iteration":149,"passed_time":10.36265562,"remaining_time":24.17952977},
{"learn":[0.0104329547],"iteration":150,"passed_time":10.40894574,"remaining_time":24.057762},
{"learn":[0.01029635906],"iteration":151,"passed_time":10.52319849,"remaining_time":24.09258601},
{"learn":[0.01018807607],"iteration":152,"passed_time":10.57169025,"remaining_time":23.9763171},
{"learn":[0.01011374908],"iteration":153,"passed_time":10.62164923,"remaining_time":23.8642249},
{"learn":[0.009967888439],"iteration":154,"passed_time":10.66224452,"remaining_time":23.73209264},
{"learn":[0.009872246455],"iteration":155,"passed_time":10.70477848,"remaining_time":23.60540896},
{"learn":[0.009733833959],"iteration":156,"passed_time":10.74549577,"remaining_time":23.47582833},
{"learn":[0.009583801586],"iteration":157,"passed_time":10.7896855,"remaining_time":23.35488886},
{"learn":[0.009528474626],"iteration":158,"passed_time":10.83778022,"remaining_time":23.24328965},
{"learn":[0.009446170136],"iteration":159,"passed_time":10.87894275,"remaining_time":23.11775335},
{"learn":[0.009326506542],"iteration":160,"passed_time":10.92548442,"remaining_time":23.00459142},
{"learn":[0.009210481054],"iteration":161,"passed_time":10.96505703,"remaining_time":22.87771158},
{"learn":[0.009128034906],"iteration":162,"passed_time":11.00875513,"remaining_time":22.76043238},
{"learn":[0.009050049886],"iteration":163,"passed_time":11.05044734,"remaining_time":22.63994089},
{"learn":[0.008963029156],"iteration":164,"passed_time":11.08707242,"remaining_time":22.51011674},
{"learn":[0.008883220407],"iteration":165,"passed_time":11.12333267,"remaining_time":22.3806814},
{"learn":[0.008832450753],"iteration":166,"passed_time":11.16845116,"remaining_time":22.27002536},
{"learn":[0.008712814002],"iteration":167,"passed_time":11.21210847,"remaining_time":22.15726197},
{"learn":[0.008525508608],"iteration":168,"passed_time":11.2598051,"remaining_time":22.05322774},
{"learn":[0.008355120902],"iteration":169,"passed_time":11.30303782,"remaining_time":21.94119106},
{"learn":[0.008200791166],"iteration":170,"passed_time":11.35587883,"remaining_time":21.84844523},
{"learn":[0.008132112677],"iteration":171,"passed_time":11.39915313,"remaining_time":21.73791992},
{"learn":[0.008079062132],"iteration":172,"passed_time":11.43484854,"remaining_time":21.61384667},
{"learn":[0.007985089309],"iteration":173,"passed_time":11.48557107,"remaining_time":21.51894351},
{"learn":[0.007907919582],"iteration":174,"passed_time":11.53172457,"remaining_time":21.41605991},
{"learn":[0.007830118389],"iteration":175,"passed_time":11.57412845,"remaining_time":21.30691828},
{"learn":[0.00772996116],"iteration":176,"passed_time":11.62219213,"remaining_time":21.20885908},
{"learn":[0.007668090772],"iteration":177,"passed_time":11.68374758,"remaining_time":21.13576809},
{"learn":[0.007556615523],"iteration":178,"passed_time":11.7290349,"remaining_time":21.03363242},
{"learn":[0.007487988944],"iteration":179,"passed_time":11.77261312,"remaining_time":20.92909},
{"learn":[0.007406734352],"iteration":180,"passed_time":11.81502584,"remaining_time":20.82316709},
{"learn":[0.00736185689],"iteration":181,"passed_time":11.85819964,"remaining_time":20.7192719},
{"learn":[0.007258909373],"iteration":182,"passed_time":11.90522464,"remaining_time":20.62271154},
{"learn":[0.00712152622],"iteration":183,"passed_time":11.95034255,"remaining_time":20.52341438},
{"learn":[0.007079651468],"iteration":184,"passed_time":12.00321451,"remaining_time":20.43790579},
{"learn":[0.006993183037],"iteration":185,"passed_time":12.04065698,"remaining_time":20.32670049},
{"learn":[0.006891575404],"iteration":186,"passed_time":12.07922162,"remaining_time":20.21816239},
{"learn":[0.006838353119],"iteration":187,"passed_time":12.11612733,"remaining_time":20.10761558},
{"learn":[0.006784866721],"iteration":188,"passed_time":12.15957306,"remaining_time":20.00860963},
{"learn":[0.006720328567],"iteration":189,"passed_time":12.20116881,"remaining_time":19.90717016},
{"learn":[0.006653806722],"iteration":190,"passed_time":12.2504802,"remaining_time":19.8188397},
{"learn":[0.006567019961],"iteration":191,"passed_time":12.2939603,"remaining_time":19.72156132},
{"learn":[0.006497202195],"iteration":192,"passed_time":12.3390985,"remaining_time":19.62747792},
{"learn":[0.006390393892],"iteration":193,"passed_time":12.38902606,"remaining_time":19.54145348},
{"learn":[0.006321834483],"iteration":194,"passed_time":12.43132169,"remaining_time":19.44386214},
{"learn":[0.006265494731],"iteration":195,"passed_time":12.47792678,"remaining_time":19.35351908},
{"learn":[0.006236110953],"iteration":196,"passed_time":12.52085974,"remaining_time":19.25797209},
{"learn":[0.006187715911],"iteration":197,"passed_time":12.56303925,"remaining_time":19.16180734},
{"learn":[0.006086009742],"iteration":198,"passed_time":12.60576022,"remaining_time":19.06700415},
{"learn":[0.006055192423],"iteration":199,"passed_time":12.6532248,"remaining_time":18.97983721},
{"learn":[0.005986688862],"iteration":200,"passed_time":12.69856146,"remaining_time":18.88989988},
{"learn":[0.00590014248],"iteration":201,"passed_time":12.7438827,"remaining_time":18.80038141},
{"learn":[0.005868176168],"iteration":202,"passed_time":12.78696488,"remaining_time":18.7080225},
{"learn":[0.005812559604],"iteration":203,"passed_time":12.83659727,"remaining_time":18.62565095},
{"learn":[0.005718389153],"iteration":204,"passed_time":12.88377353,"remaining_time":18.54006434},
{"learn":[0.005609426417],"iteration":205,"passed_time":12.9177788,"remaining_time":18.43605324},
{"learn":[0.005578978947],"iteration":206,"passed_time":12.95719674,"remaining_time":18.34037993},
{"learn":[0.005533865611],"iteration":207,"passed_time":12.99467758,"remaining_time":18.24252814},
{"learn":[0.005492862051],"iteration":208,"passed_time":13.03566058,"remaining_time":18.15013028},
{"learn":[0.005457329668],"iteration":209,"passed_time":13.07510527,"remaining_time":18.05609775},
{"learn":[0.005406502996],"iteration":210,"passed_time":13.12049551,"remaining_time":17.97072607},
{"learn":[0.005369297708],"iteration":211,"passed_time":13.16708934,"remaining_time":17.88736665},
{"learn":[0.005330915105],"iteration":212,"passed_time":13.21028977,"remaining_time":17.79978011},
{"learn":[0.005301351506],"iteration":213,"passed_time":13.2498635,"remaining_time":17.7077615},
{"learn":[0.005251060313],"iteration":214,"passed_time":13.28844214,"remaining_time":17.61491168},
{"learn":[0.005211615311],"iteration":215,"passed_time":13.33384243,"remaining_time":17.53153356},
{"learn":[0.005173460107],"iteration":216,"passed_time":13.37931433,"remaining_time":17.44859887},
{"learn":[0.005135825257],"iteration":217,"passed_time":13.42425144,"remaining_time":17.36531608},
{"learn":[0.005091099198],"iteration":218,"passed_time":13.46906172,"remaining_time":17.28222074},
{"learn":[0.005061428109],"iteration":219,"passed_time":13.52070634,"remaining_time":17.2081717},
{"learn":[0.005003283941],"iteration":220,"passed_time":13.56397244,"remaining_time":17.12374801},
{"learn":[0.004949198578],"iteration":221,"passed_time":13.60035827,"remaining_time":17.03107927},
{"learn":[0.004906241163],"iteration":222,"passed_time":13.64911653,"remaining_time":16.95428377},
{"learn":[0.004867546337],"iteration":223,"passed_time":13.69333856,"remaining_time":16.87214929},
{"learn":[0.004826567931],"iteration":224,"passed_time":13.73552156,"remaining_time":16.78785968},
{"learn":[0.004796073382],"iteration":225,"passed_time":13.78000692,"remaining_time":16.70673405},
{"learn":[0.004749578805],"iteration":226,"passed_time":13.82457836,"remaining_time":16.62603476},
{"learn":[0.004713138992],"iteration":227,"passed_time":13.87200424,"remaining_time":16.54905769},
{"learn":[0.004685407439],"iteration":228,"passed_time":13.91041338,"remaining_time":16.46166823},
{"learn":[0.004644014565],"iteration":229,"passed_time":13.94935123,"remaining_time":16.37532536},
{"learn":[0.004624735497],"iteration":230,"passed_time":13.9851871,"remaining_time":16.28578065},
{"learn":[0.004563226978],"iteration":231,"passed_time":14.02235311,"remaining_time":16.19823549},
{"learn":[0.004522514815],"iteration":232,"passed_time":14.06863298,"remaining_time":16.12156655},
{"learn":[0.004453736285],"iteration":233,"passed_time":14.11457351,"remaining_time":16.0447716},
{"learn":[0.004429800696],"iteration":234,"passed_time":14.15894249,"remaining_time":15.96646707},
{"learn":[0.004375867429],"iteration":235,"passed_time":14.19832964,"remaining_time":15.88287723},
{"learn":[0.004326813448],"iteration":236,"passed_time":14.24517669,"remaining_time":15.80793868},
{"learn":[0.004290259629],"iteration":237,"passed_time":14.28215998,"remaining_time":15.7223778},
{"learn":[0.004273791808],"iteration":238,"passed_time":14.32185043,"remaining_time":15.64017975},
{"learn":[0.004249835378],"iteration":239,"passed_time":14.35809984,"remaining_time":15.55460816},
{"learn":[0.004224643989],"iteration":240,"passed_time":14.4036075,"remaining_time":15.47939561},
{"learn":[0.004192927736],"iteration":241,"passed_time":14.44527579,"remaining_time":15.40033535},
{"learn":[0.004168998089],"iteration":242,"passed_time":14.4856924,"remaining_time":15.32025905},
{"learn":[0.004133344915],"iteration":243,"passed_time":14.53322404,"remaining_time":15.24797276},
{"learn":[0.004096666152],"iteration":244,"passed_time":14.58345106,"remaining_time":15.17869396},
{"learn":[0.004080012118],"iteration":245,"passed_time":14.62699445,"remaining_time":15.10266907},
{"learn":[0.004054571482],"iteration":246,"passed_time":14.6687152,"remaining_time":15.02504027},
{"learn":[0.004031497645],"iteration":247,"passed_time":14.71018983,"remaining_time":14.94745095},
{"learn":[0.003995878652],"iteration":248,"passed_time":14.75126053,"remaining_time":14.86974455},
{"learn":[0.003969514081],"iteration":249,"passed_time":14.7953498,"remaining_time":14.7953498},
{"learn":[0.00395288118],"iteration":250,"passed_time":14.83788135,"remaining_time":14.71965122},
{"learn":[0.003935841277],"iteration":251,"passed_time":14.88173974,"remaining_time":14.64552165},
{"learn":[0.003923490678],"iteration":252,"passed_time":14.92332616,"remaining_time":14.56941329},
{"learn":[0.003910044514],"iteration":253,"passed_time":14.96144851,"remaining_time":14.49022178},
{"learn":[0.003880349813],"iteration":254,"passed_time":14.99732796,"remaining_time":14.40919745},
{"learn":[0.003856092563],"iteration":255,"passed_time":15.04459372,"remaining_time":14.33937839},
{"learn":[0.003821591228],"iteration":256,"passed_time":15.09224601,"remaining_time":14.27010032},
{"learn":[0.003798423735],"iteration":257,"passed_time":15.13223159,"remaining_time":14.19379862},
{"learn":[0.003764651684],"iteration":258,"passed_time":15.17025614,"remaining_time":14.11595262},
{"learn":[0.003738029191],"iteration":259,"passed_time":15.21453479,"remaining_time":14.04418596},
{"learn":[0.003706905855],"iteration":260,"passed_time":15.26189925,"remaining_time":13.97545563},
{"learn":[0.003672658106],"iteration":261,"passed_time":15.30039677,"remaining_time":13.8988337},
{"learn":[0.003647996752],"iteration":262,"passed_time":15.34207464,"remaining_time":13.82536764},
{"learn":[0.003625689714],"iteration":263,"passed_time":15.38399798,"remaining_time":13.75236183},
{"learn":[0.003611213928],"iteration":264,"passed_time":15.42556914,"remaining_time":13.6792783},
{"learn":[0.003587979504],"iteration":265,"passed_time":15.4670521,"remaining_time":13.6063541},
{"learn":[0.003563070265],"iteration":266,"passed_time":15.50588641,"remaining_time":13.53135406},
{"learn":[0.003532405197],"iteration":267,"passed_time":15.54775829,"remaining_time":13.45925344},
{"learn":[0.003510424845],"iteration":268,"passed_time":15.59106935,"remaining_time":13.38861345},
{"learn":[0.003489850956],"iteration":269,"passed_time":15.63130267,"remaining_time":13.31555412},
{"learn":[0.003464798669],"iteration":270,"passed_time":15.6719757,"remaining_time":13.24310862},
{"learn":[0.003436684578],"iteration":271,"passed_time":15.71244565,"remaining_time":13.1707265},
{"learn":[0.003407282136],"iteration":272,"passed_time":15.76066916,"remaining_time":13.10502527},
{"learn":[0.003389527632],"iteration":273,"passed_time":15.81045139,"remaining_time":13.04073728},
{"learn":[0.003366791666],"iteration":274,"passed_time":15.85278532,"remaining_time":12.97046071},
{"learn":[0.003346565703],"iteration":275,"passed_time":15.89625196,"remaining_time":12.90130594},
{"learn":[0.003322628069],"iteration":276,"passed_time":15.94439613,"remaining_time":12.8361023},
{"learn":[0.003308027713],"iteration":277,"passed_time":15.98638751,"remaining_time":12.76610801},
{"learn":[0.003292976412],"iteration":278,"passed_time":16.03508919,"remaining_time":12.70162979},
{"learn":[0.003266837657],"iteration":279,"passed_time":16.07112465,"remaining_time":12.62731223},
{"learn":[0.003247861131],"iteration":280,"passed_time":16.11301511,"remaining_time":12.55783028},
{"learn":[0.003230656555],"iteration":281,"passed_time":16.15960323,"remaining_time":12.49217555},
{"learn":[0.003208042814],"iteration":282,"passed_time":16.20309429,"remaining_time":12.42428078},
{"learn":[0.003189634741],"iteration":283,"passed_time":16.24180489,"remaining_time":12.35292203},
{"learn":[0.003166811335],"iteration":284,"passed_time":16.28938832,"remaining_time":12.28848592},
{"learn":[0.0031520985],"iteration":285,"passed_time":16.33104057,"remaining_time":12.21972965},
{"learn":[0.00313910801],"iteration":286,"passed_time":16.37596451,"remaining_time":12.15359038},
{"learn":[0.003119325265],"iteration":287,"passed_time":16.42678454,"remaining_time":12.09193862},
{"learn":[0.003103584013],"iteration":288,"passed_time":16.46526293,"remaining_time":12.02135114},
{"learn":[0.003087684009],"iteration":289,"passed_time":16.50742556,"remaining_time":11.95365299},
{"learn":[0.003067850692],"iteration":290,"passed_time":16.55280513,"remaining_time":11.8884408},
{"learn":[0.003046194798],"iteration":291,"passed_time":16.59607736,"remaining_time":11.82186332},
{"learn":[0.003031560228],"iteration":292,"passed_time":16.63675293,"remaining_time":11.75361043},
{"learn":[0.00301526501],"iteration":293,"passed_time":16.6798429,"remaining_time":11.68723686},
{"learn":[0.002999751561],"iteration":294,"passed_time":16.73254445,"remaining_time":11.62770038},
{"learn":[0.002981883482],"iteration":295,"passed_time":16.77330365,"remaining_time":11.55997954},
{"learn":[0.002961448479],"iteration":296,"passed_time":16.81508682,"remaining_time":11.49314015},
{"learn":[0.002937169106],"iteration":297,"passed_time":16.86245332,"remaining_time":11.4302536},
{"learn":[0.002919550174],"iteration":298,"passed_time":16.90654514,"remaining_time":11.36526947},
{"learn":[0.002901801458],"iteration":299,"passed_time":16.95002482,"remaining_time":11.30001655},
{"learn":[0.002876020171],"iteration":300,"passed_time":16.98922092,"remaining_time":11.23207629},
{"learn":[0.002862345066],"iteration":301,"passed_time":17.03769406,"remaining_time":11.17040869},
{"learn":[0.002846384884],"iteration":302,"passed_time":17.07854618,"remaining_time":11.10387326},
{"learn":[0.002827554975],"iteration":303,"passed_time":17.11291087,"remaining_time":11.03332412},
{"learn":[0.002812861586],"iteration":304,"passed_time":17.14673544,"remaining_time":10.96266692},
{"learn":[0.002799027932],"iteration":305,"passed_time":17.19180959,"remaining_time":10.89938255},
{"learn":[0.002788825751],"iteration":306,"passed_time":17.23319121,"remaining_time":10.83389545},
{"learn":[0.00277417861],"iteration":307,"passed_time":17.27238319,"remaining_time":10.76719991},
{"learn":[0.002753398964],"iteration":308,"passed_time":17.31155355,"remaining_time":10.70066902},
{"learn":[0.002738012756],"iteration":309,"passed_time":17.34245255,"remaining_time":10.62924511},
{"learn":[0.002724125066],"iteration":310,"passed_time":17.3705984,"remaining_time":10.55640867},
{"learn":[0.002707619111],"iteration":311,"passed_time":17.40316262,"remaining_time":10.48652106},
{"learn":[0.002691235203],"iteration":312,"passed_time":17.42937478,"remaining_time":10.41307695},
{"learn":[0.002675522401],"iteration":313,"passed_time":17.45870398,"remaining_time":10.34178006},
{"learn":[0.002662890203],"iteration":314,"passed_time":17.48549394,"remaining_time":10.26925835},
{"learn":[0.002650165111],"iteration":315,"passed_time":17.50960226,"remaining_time":10.19546461},
{"learn":[0.002627450568],"iteration":316,"passed_time":17.53823666,"remaining_time":10.12459719},
{"learn":[0.002611767287],"iteration":317,"passed_time":17.56712943,"remaining_time":10.05414326},
{"learn":[0.002595015578],"iteration":318,"passed_time":17.59004757,"remaining_time":9.980559907},
{"learn":[0.00258107395],"iteration":319,"passed_time":17.61915593,"remaining_time":9.91077521},
{"learn":[0.002569118724],"iteration":320,"passed_time":17.64262578,"remaining_time":9.838099736},
{"learn":[0.002557989619],"iteration":321,"passed_time":17.66767215,"remaining_time":9.766601376},
{"learn":[0.00254823221],"iteration":322,"passed_time":17.69072488,"remaining_time":9.694298153},
{"learn":[0.00252361095],"iteration":323,"passed_time":17.71848102,"remaining_time":9.624853886},
{"learn":[0.002509585733],"iteration":324,"passed_time":17.74609965,"remaining_time":9.555592122},
{"learn":[0.002491848347],"iteration":325,"passed_time":17.76828554,"remaining_time":9.483686148},
{"learn":[0.00247809969],"iteration":326,"passed_time":17.79670294,"remaining_time":9.415381064},
{"learn":[0.002463914577],"iteration":327,"passed_time":17.82145972,"remaining_time":9.345399608},
{"learn":[0.002452891148],"iteration":328,"passed_time":17.85117808,"remaining_time":9.27827189},
{"learn":[0.002439326818],"iteration":329,"passed_time":17.88017785,"remaining_time":9.211000713},
{"learn":[0.002430741496],"iteration":330,"passed_time":17.90589706,"remaining_time":9.14228581},
{"learn":[0.002417420397],"iteration":331,"passed_time":17.93295157,"remaining_time":9.074505613},
{"learn":[0.002404053554],"iteration":332,"passed_time":17.95900782,"remaining_time":9.006469387},
{"learn":[0.002391865026],"iteration":333,"passed_time":17.98492498,"remaining_time":8.938615412},
{"learn":[0.002381478217],"iteration":334,"passed_time":18.0058614,"remaining_time":8.868558601},
{"learn":[0.002371118302],"iteration":335,"passed_time":18.03272528,"remaining_time":8.801687341},
{"learn":[0.002360563868],"iteration":336,"passed_time":18.05552626,"remaining_time":8.733088369},
{"learn":[0.002348510222],"iteration":337,"passed_time":18.08275135,"remaining_time":8.666880826},
{"learn":[0.002336909506],"iteration":338,"passed_time":18.10837118,"remaining_time":8.600140886},
{"learn":[0.002323848963],"iteration":339,"passed_time":18.13433043,"remaining_time":8.533802556},
{"learn":[0.002311474842],"iteration":340,"passed_time":18.16288708,"remaining_time":8.468912156},
{"learn":[0.002296628242],"iteration":341,"passed_time":18.18985671,"remaining_time":8.403501053},
{"learn":[0.00228699235],"iteration":342,"passed_time":18.21647238,"remaining_time":8.338152082},
{"learn":[0.002275332289],"iteration":343,"passed_time":18.24156817,"remaining_time":8.272339052},
{"learn":[0.002260916179],"iteration":344,"passed_time":18.26392035,"remaining_time":8.205529431},
{"learn":[0.002243623635],"iteration":345,"passed_time":18.29171882,"remaining_time":8.141400861},
{"learn":[0.002234874579],"iteration":346,"passed_time":18.32529125,"remaining_time":8.080027556},
{"learn":[0.002222010751],"iteration":347,"passed_time":18.35111517,"remaining_time":8.015429614},
{"learn":[0.002215963526],"iteration":348,"passed_time":18.37288439,"remaining_time":7.949299548},
{"learn":[0.002197796284],"iteration":349,"passed_time":18.40249787,"remaining_time":7.886784803},
{"learn":[0.002178920081],"iteration":350,"passed_time":18.42753566,"remaining_time":7.822515136},
{"learn":[0.002169605602],"iteration":351,"passed_time":18.45430258,"remaining_time":7.759195403},
{"learn":[0.002158100109],"iteration":352,"passed_time":18.4802685,"remaining_time":7.695749204},
{"learn":[0.002150468381],"iteration":353,"passed_time":18.50458619,"remaining_time":7.631834983},
{"learn":[0.002138528295],"iteration":354,"passed_time":18.53166878,"remaining_time":7.569273165},
{"learn":[0.002125918048],"iteration":355,"passed_time":18.55709853,"remaining_time":7.506242101},
{"learn":[0.002110490047],"iteration":356,"passed_time":18.58301778,"remaining_time":7.443617765},
{"learn":[0.002105682685],"iteration":357,"passed_time":18.60789085,"remaining_time":7.380783522},
{"learn":[0.002095115472],"iteration":358,"passed_time":18.63278538,"remaining_time":7.31816919},
{"learn":[0.002084067152],"iteration":359,"passed_time":18.66635824,"remaining_time":7.259139314},
{"learn":[0.002072409051],"iteration":360,"passed_time":18.69291995,"remaining_time":7.197550895},
{"learn":[0.002050022638],"iteration":361,"passed_time":18.7196555,"remaining_time":7.136222261},
{"learn":[0.00203870861],"iteration":362,"passed_time":18.74026737,"remaining_time":7.072773085},
{"learn":[0.002030928214],"iteration":363,"passed_time":18.76215813,"remaining_time":7.010037103},
{"learn":[0.002022841175],"iteration":364,"passed_time":18.78840742,"remaining_time":6.949136992},
{"learn":[0.002016322566],"iteration":365,"passed_time":18.81114377,"remaining_time":6.88714007},
{"learn":[0.002005986477],"iteration":366,"passed_time":18.83943717,"remaining_time":6.827370962},
{"learn":[0.00199821026],"iteration":367,"passed_time":18.86314056,"remaining_time":6.766126507},
{"learn":[0.001988389659],"iteration":368,"passed_time":18.89740725,"remaining_time":6.708835638},
{"learn":[0.001981657888],"iteration":369,"passed_time":18.93212195,"remaining_time":6.651826631},
{"learn":[0.0019727546],"iteration":370,"passed_time":18.96283499,"remaining_time":6.593546397},
{"learn":[0.001960873154],"iteration":371,"passed_time":18.98998946,"remaining_time":6.53418992},
{"learn":[0.001948435899],"iteration":372,"passed_time":19.01809347,"remaining_time":6.475329413},
{"learn":[0.001938546306],"iteration":373,"passed_time":19.03739108,"remaining_time":6.413666515},
{"learn":[0.001922537269],"iteration":374,"passed_time":19.0662734,"remaining_time":6.355424467},
{"learn":[0.001918121794],"iteration":375,"passed_time":19.09256574,"remaining_time":6.296484445},
{"learn":[0.001904655253],"iteration":376,"passed_time":19.11813548,"remaining_time":6.237481868},
{"learn":[0.001900837705],"iteration":377,"passed_time":19.14407127,"remaining_time":6.178774326},
{"learn":[0.001888143704],"iteration":378,"passed_time":19.17255817,"remaining_time":6.121054191},
{"learn":[0.001882032405],"iteration":379,"passed_time":19.1954411,"remaining_time":6.061718243},
{"learn":[0.001879612191],"iteration":380,"passed_time":19.22306866,"remaining_time":6.004055564},
{"learn":[0.001873233239],"iteration":381,"passed_time":19.25424236,"remaining_time":5.947645547},
{"learn":[0.001864022262],"iteration":382,"passed_time":19.28374318,"remaining_time":5.890856273},
{"learn":[0.001856001042],"iteration":383,"passed_time":19.31014277,"remaining_time":5.833272295},
{"learn":[0.001849689964],"iteration":384,"passed_time":19.33283874,"remaining_time":5.77474404},
{"learn":[0.001847539619],"iteration":385,"passed_time":19.35730315,"remaining_time":5.716923728},
{"learn":[0.001834968593],"iteration":386,"passed_time":19.38463403,"remaining_time":5.66011278},
{"learn":[0.001826139024],"iteration":387,"passed_time":19.411217,"remaining_time":5.603237896},
{"learn":[0.001820518348],"iteration":388,"passed_time":19.43724541,"remaining_time":5.546360517},
{"learn":[0.001816306846],"iteration":389,"passed_time":19.46823612,"remaining_time":5.491040957},
{"learn":[0.00180581905],"iteration":390,"passed_time":19.49584776,"remaining_time":5.434903851},
{"learn":[0.001796175268],"iteration":391,"passed_time":19.5246027,"remaining_time":5.379227274},
{"learn":[0.00179103879],"iteration":392,"passed_time":19.55021578,"remaining_time":5.322832285},
{"learn":[0.00178521911],"iteration":393,"passed_time":19.57786975,"remaining_time":5.267142623},
{"learn":[0.001772136018],"iteration":394,"passed_time":19.60629519,"remaining_time":5.211799986},
{"learn":[0.001758359874],"iteration":395,"passed_time":19.63480062,"remaining_time":5.156614305},
{"learn":[0.001751033218],"iteration":396,"passed_time":19.6584441,"remaining_time":5.100301619},
{"learn":[0.001743107212],"iteration":397,"passed_time":19.68227967,"remaining_time":5.044202327},
{"learn":[0.001733641383],"iteration":398,"passed_time":19.71207937,"remaining_time":4.989774476},
{"learn":[0.001722828877],"iteration":399,"passed_time":19.73639694,"remaining_time":4.934099234},
{"learn":[0.001716831552],"iteration":400,"passed_time":19.76223918,"remaining_time":4.878956806},
{"learn":[0.001709821996],"iteration":401,"passed_time":19.78814727,"remaining_time":4.823976199},
{"learn":[0.001704415549],"iteration":402,"passed_time":19.81201079,"remaining_time":4.768647759},
{"learn":[0.001693924907],"iteration":403,"passed_time":19.83907713,"remaining_time":4.714236151},
{"learn":[0.001692145316],"iteration":404,"passed_time":19.8650548,"remaining_time":4.659704212},
{"learn":[0.001685637125],"iteration":405,"passed_time":19.89489241,"remaining_time":4.606206618},
{"learn":[0.001680853619],"iteration":406,"passed_time":19.91767418,"remaining_time":4.551213019},
{"learn":[0.00167135997],"iteration":407,"passed_time":19.94890464,"remaining_time":4.498282419},
{"learn":[0.001671357857],"iteration":408,"passed_time":19.9707964,"remaining_time":4.443380128},
{"learn":[0.001657061072],"iteration":409,"passed_time":19.9974254,"remaining_time":4.389678747},
{"learn":[0.001645506824],"iteration":410,"passed_time":20.02641443,"remaining_time":4.336620156},
{"learn":[0.00163890909],"iteration":411,"passed_time":20.05249455,"remaining_time":4.283057089},
{"learn":[0.001632138599],"iteration":412,"passed_time":20.08053907,"remaining_time":4.230040918},
{"learn":[0.001619945481],"iteration":413,"passed_time":20.10775899,"remaining_time":4.176974091},
{"learn":[0.00161331359],"iteration":414,"passed_time":20.13200936,"remaining_time":4.123423603},
{"learn":[0.001609042348],"iteration":415,"passed_time":20.16131484,"remaining_time":4.071034727},
{"learn":[0.001603960118],"iteration":416,"passed_time":20.18592454,"remaining_time":4.01782191},
{"learn":[0.001599430862],"iteration":417,"passed_time":20.20963414,"remaining_time":3.964569378},
{"learn":[0.001595611354],"iteration":418,"passed_time":20.23591131,"remaining_time":3.911954216},
{"learn":[0.001591139113],"iteration":419,"passed_time":20.26275745,"remaining_time":3.859572847},
{"learn":[0.001586431741],"iteration":420,"passed_time":20.30891357,"remaining_time":3.810936275},
{"learn":[0.001579899301],"iteration":421,"passed_time":20.34265396,"remaining_time":3.760016609},
{"learn":[0.001565061916],"iteration":422,"passed_time":20.37197803,"remaining_time":3.708374251},
{"learn":[0.001563500109],"iteration":423,"passed_time":20.40387595,"remaining_time":3.65729852},
{"learn":[0.001557759061],"iteration":424,"passed_time":20.42725547,"remaining_time":3.604809789},
{"learn":[0.001548629499],"iteration":425,"passed_time":20.4534576,"remaining_time":3.552948033},
{"learn":[0.001543496847],"iteration":426,"passed_time":20.47907068,"remaining_time":3.50110576},
{"learn":[0.001543485574],"iteration":427,"passed_time":20.49944193,"remaining_time":3.448504249},
{"learn":[0.001543479902],"iteration":428,"passed_time":20.51847095,"remaining_time":3.395830857},
{"learn":[0.001543488808],"iteration":429,"passed_time":20.54272819,"remaining_time":3.344165054},
{"learn":[0.001543474538],"iteration":430,"passed_time":20.56408715,"remaining_time":3.292162444},
{"learn":[0.001543483916],"iteration":431,"passed_time":20.58640654,"remaining_time":3.240452881},
{"learn":[0.001543478163],"iteration":432,"passed_time":20.60934056,"remaining_time":3.188974174},
{"learn":[0.001543466546],"iteration":433,"passed_time":20.63095015,"remaining_time":3.137425598},
{"learn":[0.001543475221],"iteration":434,"passed_time":20.65373941,"remaining_time":3.086190947},
{"learn":[0.001543463673],"iteration":435,"passed_time":20.67795165,"remaining_time":3.035295655},
{"learn":[0.001543458799],"iteration":436,"passed_time":20.69883798,"remaining_time":2.984043004},
{"learn":[0.001543465696],"iteration":437,"passed_time":20.71863843,"remaining_time":2.932775303},
{"learn":[0.001543451551],"iteration":438,"passed_time":20.74023906,"remaining_time":2.8819011},
{"learn":[0.001543445766],"iteration":439,"passed_time":20.76244837,"remaining_time":2.831242959},
{"learn":[0.001543450495],"iteration":440,"passed_time":20.78069843,"remaining_time":2.780184144},
{"learn":[0.001543437782],"iteration":441,"passed_time":20.8034209,"remaining_time":2.729860661},
{"learn":[0.001543440109],"iteration":442,"passed_time":20.82424324,"remaining_time":2.679417301},
{"learn":[0.001539591126],"iteration":443,"passed_time":20.84950165,"remaining_time":2.629666874},
{"learn":[0.001531362597],"iteration":444,"passed_time":20.87305738,"remaining_time":2.57981608},
{"learn":[0.001523751765],"iteration":445,"passed_time":20.89942688,"remaining_time":2.530423882},
{"learn":[0.001513775739],"iteration":446,"passed_time":20.92737119,"remaining_time":2.481321416},
{"learn":[0.001510443576],"iteration":447,"passed_time":20.9545492,"remaining_time":2.43222446},
{"learn":[0.001505905697],"iteration":448,"passed_time":20.98739596,"remaining_time":2.383869029},
{"learn":[0.001505911379],"iteration":449,"passed_time":21.00527635,"remaining_time":2.333919595},
{"learn":[0.00150590199],"iteration":450,"passed_time":21.02956217,"remaining_time":2.284808307},
{"learn":[0.001505895005],"iteration":451,"passed_time":21.05059851,"remaining_time":2.235461788},
{"learn":[0.001505891877],"iteration":452,"passed_time":21.07189172,"remaining_time":2.186266911},
{"learn":[0.001505879619],"iteration":453,"passed_time":21.09185192,"remaining_time":2.137059886},
{"learn":[0.001505865636],"iteration":454,"passed_time":21.11208883,"remaining_time":2.088008786},
{"learn":[0.001505870546],"iteration":455,"passed_time":21.13356492,"remaining_time":2.039203633},
{"learn":[0.001505852345],"iteration":456,"passed_time":21.14982955,"remaining_time":1.990027726},
{"learn":[0.001505849728],"iteration":457,"passed_time":21.16977384,"remaining_time":1.941332972},
{"learn":[0.001505832614],"iteration":458,"passed_time":21.19385453,"remaining_time":1.893132976},
{"learn":[0.001496836469],"iteration":459,"passed_time":21.22468015,"remaining_time":1.845624361},
{"learn":[0.001486104633],"iteration":460,"passed_time":21.24954352,"remaining_time":1.797683725},
{"learn":[0.001478012987],"iteration":461,"passed_time":21.27183957,"remaining_time":1.749631826},
{"learn":[0.001472805293],"iteration":462,"passed_time":21.29223774,"remaining_time":1.701539517},
{"learn":[0.001468608389],"iteration":463,"passed_time":21.31560959,"remaining_time":1.653797296},
{"learn":[0.001465479483],"iteration":464,"passed_time":21.33175764,"remaining_time":1.605616166},
{"learn":[0.001460415577],"iteration":465,"passed_time":21.34657234,"remaining_time":1.557475235},
{"learn":[0.001454787527],"iteration":466,"passed_time":21.36152829,"remaining_time":1.50948701},
{"learn":[0.00144654014],"iteration":467,"passed_time":21.37568403,"remaining_time":1.461585233},
{"learn":[0.001441933281],"iteration":468,"passed_time":21.38999869,"remaining_time":1.413837866},
{"learn":[0.001433166226],"iteration":469,"passed_time":21.40508631,"remaining_time":1.366282105},
{"learn":[0.001430182248],"iteration":470,"passed_time":21.41965047,"remaining_time":1.318831982},
{"learn":[0.001422939445],"iteration":471,"passed_time":21.43824291,"remaining_time":1.271760172},
{"learn":[0.001419188692],"iteration":472,"passed_time":21.45024225,"remaining_time":1.224432433},
{"learn":[0.001415652881],"iteration":473,"passed_time":21.46127992,"remaining_time":1.177201008},
{"learn":[0.001410558444],"iteration":474,"passed_time":21.47065254,"remaining_time":1.130034344},
{"learn":[0.001402746869],"iteration":475,"passed_time":21.48168867,"remaining_time":1.083110353},
{"learn":[0.001398670484],"iteration":476,"passed_time":21.48869952,"remaining_time":1.036142744},
{"learn":[0.001389488275],"iteration":477,"passed_time":21.49485828,"remaining_time":0.9893031006},
{"learn":[0.001386687878],"iteration":478,"passed_time":21.50130312,"remaining_time":0.942645857},
{"learn":[0.001382253734],"iteration":479,"passed_time":21.50733442,"remaining_time":0.8961389341},
{"learn":[0.001372429488],"iteration":480,"passed_time":21.51352055,"remaining_time":0.8498064251},
{"learn":[0.001363039084],"iteration":481,"passed_time":21.51935431,"remaining_time":0.8036273392},
{"learn":[0.001356114202],"iteration":482,"passed_time":21.52540235,"remaining_time":0.7576228572},
{"learn":[0.001352895467],"iteration":483,"passed_time":21.53144986,"remaining_time":0.7117834665},
{"learn":[0.001345011366],"iteration":484,"passed_time":21.5378075,"remaining_time":0.6661177576},
{"learn":[0.001339078723],"iteration":485,"passed_time":21.543723,"remaining_time":0.6206010741},
{"learn":[0.001334488304],"iteration":486,"passed_time":21.54974517,"remaining_time":0.5752498712},
{"learn":[0.001324932858],"iteration":487,"passed_time":21.55556485,"remaining_time":0.5300548733},
{"learn":[0.001324932858],"iteration":488,"passed_time":21.56024338,"remaining_time":0.4849952499},
{"learn":[0.001319399521],"iteration":489,"passed_time":21.5671204,"remaining_time":0.4401453142},
{"learn":[0.001316916999],"iteration":490,"passed_time":21.57325295,"remaining_time":0.3954364084},
{"learn":[0.001311495455],"iteration":491,"passed_time":21.579863,"remaining_time":0.3508920813},
{"learn":[0.001307332856],"iteration":492,"passed_time":21.58577088,"remaining_time":0.3064916758},
{"learn":[0.001304339304],"iteration":493,"passed_time":21.59179934,"remaining_time":0.262248575},
{"learn":[0.001299989859],"iteration":494,"passed_time":21.59820323,"remaining_time":0.218163669},
{"learn":[0.001293518205],"iteration":495,"passed_time":21.60452415,"remaining_time":0.1742300335},
{"learn":[0.001281301134],"iteration":496,"passed_time":21.61028112,"remaining_time":0.1304443528},
{"learn":[0.001276883713],"iteration":497,"passed_time":21.6176413,"remaining_time":0.08681783655},
{"learn":[0.0012740664],"iteration":498,"passed_time":21.62339289,"remaining_time":0.04333345268},
{"learn":[0.001265312353],"iteration":499,"passed_time":21.62948435,"remaining_time":0}
]}044683,"remaining_time":0}
]}